pcapprocessor/__init__.py
pcapprocessor/bfsRunner.py
pcapprocessor/calcQsz.py
pcapprocessor/cfgPbsWriter.py
pcapprocessor/cfgWrapper.py
pcapprocessor/cmdRunner.py
pcapprocessor/confInt.py
pcapprocessor/csvWriter.py
pcapprocessor/dceRunner.py
pcapprocessor/exe_comm.py
pcapprocessor/metricStats.py
pcapprocessor/pbsWriter.py
pcapprocessor/pp_trace.py
pcapprocessor/wafCmd.py
pcapprocessor/xscaleArray.py
pcapprocessor-0.1.0.dist-info/LICENSE
pcapprocessor-0.1.0.dist-info/METADATA
pcapprocessor-0.1.0.dist-info/WHEEL
pcapprocessor-0.1.0.dist-info/top_level.txt
pcapprocessor-0.1.0.dist-info/RECORD
