Metadata-Version: 2.1
Name: pcapprocessor
Version: 0.1.0
Summary: A simple PCAP processor
Home-page: UNKNOWN
Author: Siddharth Gangadhar, Truc Anh N Nguyen, Santosh Gondi
Author-email: lordlabakdas.code@gmail.com
Maintainer: Siddharth Gangadhar
Maintainer-email: lordlabakdas.code@gmail.com
License: UNKNOWN
Keywords: pcap,python,network,security,metrics,analysis
Platform: UNKNOWN
License-File: LICENSE
Requires-Dist: PyYAML (==5.4.1)
Requires-Dist: attrs (==21.2.0)
Requires-Dist: backports.entry-points-selectable (==1.1.0)
Requires-Dist: cfgv (==3.3.1)
Requires-Dist: distlib (==0.3.3)
Requires-Dist: filelock (==3.2.1)
Requires-Dist: identify (==2.3.0)
Requires-Dist: importlib-metadata (==4.8.1)
Requires-Dist: iniconfig (==1.1.1)
Requires-Dist: nodeenv (==1.6.0)
Requires-Dist: numpy (==1.21.5)
Requires-Dist: packaging (==21.0)
Requires-Dist: platformdirs (==2.4.0)
Requires-Dist: pluggy (==1.0.0)
Requires-Dist: pre-commit (==2.15.0)
Requires-Dist: py (==1.10.0)
Requires-Dist: pyparsing (==2.4.7)
Requires-Dist: pytest (==6.2.5)
Requires-Dist: scipy (==1.10.1)
Requires-Dist: six (==1.16.0)
Requires-Dist: toml (==0.10.2)
Requires-Dist: typing-extensions (>=4.0.1)
Requires-Dist: virtualenv (==20.8.1)
Requires-Dist: zipp (==3.6.0)
